Metadata-Version: 1.2
Name: publab
Version: 0.0.1
Summary: Tools for publication management in GitLab.
Home-page: https://github.com/riga/publab
Author: The publab Authors
Author-email: publab@googlegroups.com
License: BSD-3-Clause
Keywords: publication gitlab
Platform: UNKNOWN
Classifier: Programming Language :: Python
Classifier: Programming Language :: Python :: 2
Classifier: Programming Language :: Python :: 3
Classifier: Development Status :: 4 - Beta
Classifier: Operating System :: OS Independent
Classifier: License :: OSI Approved :: BSD License
Classifier: Intended Audience :: Developers
Classifier: Intended Audience :: Science/Research
Classifier: Intended Audience :: Information Technology
Requires-Python: >=2.7, !=3.0.*, !=3.1.*, !=3.2.*, <4'
